{
  "1319222775168372757": {
    "style": "outback aussie cunt",
    "enabled": false
  },
  "1433639707308462090": {
    "style": "sarcastic sassy bitch",
    "enabled": false
  },
  "1315404395118329908": {
    "style": "witch",
    "enabled": false
  },
  "275505299845021697": {
    "style": "Monkey boy",
    "enabled": false
  },
  "1312449822661546008": {
    "style": "leader",
    "enabled": false
  },
  "1332828845174165587": {
    "style": "Hard working mechanic",
    "enabled": false
  },
  "400676292925587456": {
    "style": "Sleepy joe with feminie attitude",
    "enabled": false
  },
  "402272667467644928": {
    "style": "Sophisticated teacher",
    "enabled": false
  },
  "400865790779195392": {
    "style": "Aussie Plumber",
    "enabled": false
  },
  "851837173292204052": {
    "style": "Math wizz",
    "enabled": false
  },
  "1315331301326323782": {
    "style": "Vampire",
    "enabled": false
  },
  "533880942151073822": {
    "style": "Twitch Streamer",
    "enabled": false
  },
  "276923819766185984": {
    "style": "Sophisticated Canadian",
    "enabled": false
  },
  "513944655780642831": {
    "style": "AudioPhile",
    "enabled": false
  },
  "1153949297549774888": {
    "style": "candian seacow",
    "enabled": false
  },
  "992633641484157048": {
    "style": "donald trump",
    "enabled": false
  }
}